vpc_lattice/__init__.py
vpc_lattice/py.typed
vpc_lattice/_jsii/__init__.py
vpc_lattice/_jsii/aws-vpclattice-prealpha@0.4.12.jsii.tgz
aws_vpclattice_prealpha-0.4.12.dist-info/LICENSE
aws_vpclattice_prealpha-0.4.12.dist-info/METADATA
aws_vpclattice_prealpha-0.4.12.dist-info/WHEEL
aws_vpclattice_prealpha-0.4.12.dist-info/top_level.txt
aws_vpclattice_prealpha-0.4.12.dist-info/RECORD
